android_prober/__init__.py
android_prober/app.py
android_prober/proxy_utils.py
android_prober/apis/__init__.py
android_prober/apis/audio.py
android_prober/apis/battery.py
android_prober/apis/bluetooth.py
android_prober/apis/brightness.py
android_prober/apis/call.py
android_prober/apis/camera.py
android_prober/apis/email.py
android_prober/apis/filechooser.py
android_prober/apis/flash.py
android_prober/apis/gps.py
android_prober/apis/notification.py
android_prober/apis/runtime_permission.py
android_prober/apis/sensors.py
android_prober/apis/service.py
android_prober/apis/tts.py
android_prober/apis/vibrator.py
android_prober/facades/__init__.py
android_prober/facades/audio.py
android_prober/facades/battery.py
android_prober/facades/bluetooth.py
android_prober/facades/brightness.py
android_prober/facades/call.py
android_prober/facades/camera.py
android_prober/facades/email.py
android_prober/facades/filechooser.py
android_prober/facades/flash.py
android_prober/facades/gps.py
android_prober/facades/notification.py
android_prober/facades/runtime_permission.py
android_prober/facades/sensor.py
android_prober/facades/service.py
android_prober/facades/tts.py
android_prober/facades/vibrator.py
android_prober/platforms/android/bluetooth.py
android_prober/platforms/android/realtime_service.py
android_prober/platforms/android/runtime_permission.py
android_prober/platforms/android/service.py
android_prober/platforms/generics/audio.py
android_prober/platforms/generics/battery.py
android_prober/platforms/generics/brightness.py
android_prober/platforms/generics/call.py
android_prober/platforms/generics/camera.py
android_prober/platforms/generics/email.py
android_prober/platforms/generics/filechooser.py
android_prober/platforms/generics/flash.py
android_prober/platforms/generics/gps.py
android_prober/platforms/generics/notification.py
android_prober/platforms/generics/sensor.py
android_prober/platforms/generics/tts.py
android_prober/platforms/generics/vibrator.py
android_prober-0.1.7.dist-info/LICENSE
android_prober-0.1.7.dist-info/METADATA
android_prober-0.1.7.dist-info/WHEEL
android_prober-0.1.7.dist-info/top_level.txt
android_prober-0.1.7.dist-info/RECORD
