Metadata-Version: 2.1
Name: android-prober
Version: 0.1.7
Summary: Library for test android api's via service
Home-page: https://github.com/gunaNeelamegam
Author: GunaNeelamegam
Author-email: gunag77730@gmail.com
License: Apacher License 2.0
License-File: LICENSE
Requires-Dist: flask
Requires-Dist: kivy
Requires-Dist: oscpy
Requires-Dist: plyer
Requires-Dist: swagger-gen
Requires-Dist: pyjnius ==1.6.1
